yad.py
yad-0.9.14.data/scripts/gdie
yad-0.9.14.dist-info/DESCRIPTION.rst
yad-0.9.14.dist-info/METADATA
yad-0.9.14.dist-info/RECORD
yad-0.9.14.dist-info/WHEEL
yad-0.9.14.dist-info/metadata.json
yad-0.9.14.dist-info/top_level.txt
