Metadata-Version: 2.0
Name: yad
Version: 0.9.14
Summary: A python interface for the Yad program
Home-page: https://gitlab.com/dvenkatsagar/python-yad/
Author: Sagar D V
Author-email: dvenkatsagar@gmail.com
License: GPL3
Download-URL: https://gitlab.com/dvenkatsagar/python-yad/repository/archive.zip
Platform: UNKNOWN
Classifier: Development Status :: 5 - Production/Stable
Classifier: Intended Audience :: Developers
Classifier: License :: OSI Approved :: GNU General Public License v3 or later (GPLv3+)
Classifier: Natural Language :: English
Classifier: Operating System :: MacOS
Classifier: Operating System :: POSIX
Classifier: Programming Language :: Python :: 2
Classifier: Programming Language :: Python :: 3
Classifier: Topic :: Utilities
Requires-Dist: pexpect (>=3.3)
